Metadata-Version: 1.0
Name: GaussianBinomial-probability-dist03
Version: 0.3
Summary: Gaussian and Binomial distributions
Home-page: UNKNOWN
Author: Ali Rezghi
Author-email: UNKNOWN
License: UNKNOWN
Platform: UNKNOWN
